ezqt_app/__init__.py
ezqt_app/app.py
ezqt_app/main.py
ezqt_app/cli/__init__.py
ezqt_app/cli/create_qm_files.py
ezqt_app/cli/main.py
ezqt_app/cli/runner.py
ezqt_app/cli/__pycache__/__init__.cpython-311.pyc
ezqt_app/cli/__pycache__/main.cpython-311.pyc
ezqt_app/cli/__pycache__/runner.cpython-311.pyc
ezqt_app/kernel/__init__.py
ezqt_app/kernel/app_components.py
ezqt_app/kernel/app_resources.py
ezqt_app/kernel/app_settings.py
ezqt_app/kernel/common.py
ezqt_app/kernel/globals.py
ezqt_app/kernel/qt_config.py
ezqt_app/kernel/ui_main.py
ezqt_app/kernel/.backup/app_functions.py.backup
ezqt_app/kernel/.backup/app_resources.py.backup
ezqt_app/kernel/.backup/translation_config.py.backup
ezqt_app/kernel/.backup/translation_config_facade.py.backup
ezqt_app/kernel/.backup/translation_helpers.py.backup
ezqt_app/kernel/.backup/translation_helpers_facade.py.backup
ezqt_app/kernel/.backup/translation_manager.py.backup
ezqt_app/kernel/.backup/translation_manager_facade.py.backup
ezqt_app/kernel/.backup/ui_functions.py.backup
ezqt_app/kernel/__pycache__/__init__.cpython-311.pyc
ezqt_app/kernel/__pycache__/app_components.cpython-311.pyc
ezqt_app/kernel/__pycache__/app_resources.cpython-311.pyc
ezqt_app/kernel/__pycache__/app_settings.cpython-311.pyc
ezqt_app/kernel/__pycache__/common.cpython-311.pyc
ezqt_app/kernel/__pycache__/early_init.cpython-311.pyc
ezqt_app/kernel/__pycache__/globals.cpython-311.pyc
ezqt_app/kernel/__pycache__/qt_config.cpython-311.pyc
ezqt_app/kernel/__pycache__/qt_hooks.cpython-311.pyc
ezqt_app/kernel/__pycache__/ui_main.cpython-311.pyc
ezqt_app/kernel/app_functions/__init__.py
ezqt_app/kernel/app_functions/assets_manager.py
ezqt_app/kernel/app_functions/config_manager.py
ezqt_app/kernel/app_functions/file_maker.py
ezqt_app/kernel/app_functions/helpers.py
ezqt_app/kernel/app_functions/kernel.py
ezqt_app/kernel/app_functions/printer.py
ezqt_app/kernel/app_functions/resource_manager.py
ezqt_app/kernel/app_functions/settings_manager.py
ezqt_app-4.0.3.post1.dist-info/licenses/LICENSE
ezqt_app-4.0.3.post1.dist-info/METADATA
ezqt_app-4.0.3.post1.dist-info/WHEEL
ezqt_app-4.0.3.post1.dist-info/entry_points.txt
ezqt_app-4.0.3.post1.dist-info/top_level.txt
ezqt_app-4.0.3.post1.dist-info/RECORD
