Metadata-Version: 2.4
Name: EzQt_App
Version: 4.0.3.post1
Summary: Lightweight framework based on PySide6 to quickly build modern desktop applications, with integrated resource, theme, and reusable component management.
Author-email: Florian Salort <floriansalort@gmail.com>
License: MIT
Keywords: application,framework
Classifier: Programming Language :: Python :: 3
Classifier: License :: OSI Approved :: MIT License
Classifier: Operating System :: OS Independent
Classifier: Development Status :: 4 - Beta
Classifier: Intended Audience :: Developers
Classifier: Topic :: Software Development :: Libraries :: Python Modules
Classifier: Topic :: Office/Business
Requires-Python: <3.13,>=3.9
License-File: LICENSE
Requires-Dist: PySide6==6.9.1
Requires-Dist: PyYaml==6.0.2
Requires-Dist: ruamel.yaml==0.18.6
Requires-Dist: colorama==0.4.6
Requires-Dist: requests==2.32.3
Requires-Dist: click>=8.0.0
Requires-Dist: ezqt-widgets>=2.0.0
Requires-Dist: langdetect
Provides-Extra: dev
Requires-Dist: pytest>=7.0.0; extra == "dev"
Requires-Dist: pytest-cov>=4.0.0; extra == "dev"
Requires-Dist: pytest-qt>=4.0.0; extra == "dev"
Requires-Dist: pytest-mock>=3.10.0; extra == "dev"
Requires-Dist: pytest-xdist>=3.0.0; extra == "dev"
Requires-Dist: flake8>=5.0.0; extra == "dev"
Requires-Dist: black>=22.0.0; extra == "dev"
Requires-Dist: mypy>=1.0.0; extra == "dev"
Dynamic: license-file
